letterpress/__init__.py
letterpress-0.0.1.dist-info/METADATA
letterpress-0.0.1.dist-info/WHEEL
letterpress-0.0.1.dist-info/top_level.txt
letterpress-0.0.1.dist-info/RECORD
