Metadata-Version: 2.1
Name: letterpress
Version: 0.0.1
Summary: batch docx generation
Home-page: https://github.com/littercodersh/letterpress
Author: LittleCoder
Author-email: i7meavnktqegm1b@qq.com
License: UNKNOWN
Platform: UNKNOWN
Classifier: Programming Language :: Python :: 3
Classifier: License :: OSI Approved :: MIT License
Classifier: Operating System :: OS Independent
Requires-Python: >=3
Requires-Dist: python-docx
Requires-Dist: xlwings
